{
  "required": true,
  "package": "gg.moonflower.pollen.core.mixin.forge",
  "compatibilityLevel": "JAVA_8",
  "minVersion": "0.8",
  "client": [
    "client.ClientPackSourceMixin",
    "client.CreateWorldScreenMixin",
    "client.LevelRendererMixin",
    "client.OptionsMixin"
  ],
  "mixins": [
    "FMLHandshakeHandlerMixin",
    "FolderRepositorySourceAccessor",
    "ForgeInternalHandlerMixin",
    "PackRepositoryAccessor",
    "PackRepositoryMixin",
    "SimpleReloadableResourceManagerMixin"
  ],
  "injectors": {
    "defaultRequire": 1
  }
}